meteostat/__init__.py
meteostat/api/__init__.py
meteostat/api/daily.py
meteostat/api/hourly.py
meteostat/api/interpolate.py
meteostat/api/inventory.py
meteostat/api/merge.py
meteostat/api/monthly.py
meteostat/api/normals.py
meteostat/api/point.py
meteostat/api/stations.py
meteostat/api/timeseries.py
meteostat/core/cache.py
meteostat/core/config.py
meteostat/core/data.py
meteostat/core/logger.py
meteostat/core/network.py
meteostat/core/parameters.py
meteostat/core/providers.py
meteostat/core/schema.py
meteostat/core/validator.py
meteostat/enumerations.py
meteostat/interpolation/__init__.py
meteostat/interpolation/idw.py
meteostat/interpolation/lapserate.py
meteostat/interpolation/nearest.py
meteostat/parameters.py
meteostat/providers/__init__.py
meteostat/providers/dwd/climat.py
meteostat/providers/dwd/daily.py
meteostat/providers/dwd/hourly.py
meteostat/providers/dwd/monthly.py
meteostat/providers/dwd/mosmix.py
meteostat/providers/dwd/poi.py
meteostat/providers/dwd/shared.py
meteostat/providers/eccc/daily.py
meteostat/providers/eccc/hourly.py
meteostat/providers/eccc/monthly.py
meteostat/providers/eccc/shared.py
meteostat/providers/index.py
meteostat/providers/meteostat/daily.py
meteostat/providers/meteostat/daily_derived.py
meteostat/providers/meteostat/hourly.py
meteostat/providers/meteostat/monthly.py
meteostat/providers/meteostat/monthly_derived.py
meteostat/providers/meteostat/shared.py
meteostat/providers/metno/forecast.py
meteostat/providers/noaa/ghcnd.py
meteostat/providers/noaa/isd_lite.py
meteostat/providers/noaa/metar.py
meteostat/py.typed
meteostat/typing.py
meteostat/utils/__init__.py
meteostat/utils/conversions.py
meteostat/utils/data.py
meteostat/utils/geo.py
meteostat/utils/parsers.py
meteostat/utils/types.py
meteostat/utils/validators.py
meteostat-2.0.0.dist-info/METADATA
meteostat-2.0.0.dist-info/WHEEL
meteostat-2.0.0.dist-info/licenses/LICENSE
meteostat-2.0.0.dist-info/RECORD
